pipa/__init__.py
pipa/pipa.py
pipa_py-0.1.0.dist-info/licenses/LICENSE
pipa_py-0.1.0.dist-info/METADATA
pipa_py-0.1.0.dist-info/WHEEL
pipa_py-0.1.0.dist-info/top_level.txt
pipa_py-0.1.0.dist-info/RECORD
