Metadata-Version: 2.4
Name: pipa.py
Version: 0.1.0
Summary: Dead simple python wrapper for pip, the package installer for the Python Package Index.
Author-email: stainlesteel <pd4500@protonmail.com>
Project-URL: Homepage, https://github.com/stainlesteel/pipa
Project-URL: Issues, https://github.com/stainlesteel/pipa/issues
Classifier: Programming Language :: Python :: 3
Classifier: License :: OSI Approved :: GNU Affero General Public License v3
Classifier: Operating System :: Unix
Requires-Python: >=3.8
License-File: LICENSE
Dynamic: license-file
